muse_pytorch/__init__.py
muse_pytorch/blocks.py
muse_pytorch/data.py
muse_pytorch/losses.py
muse_pytorch/modules.py
muse_pytorch/muse.py
muse_pytorch/utils.py
muse_pytorch-0.0.1.dist-info/LICENCE
muse_pytorch-0.0.1.dist-info/METADATA
muse_pytorch-0.0.1.dist-info/WHEEL
muse_pytorch-0.0.1.dist-info/top_level.txt
muse_pytorch-0.0.1.dist-info/RECORD
