Metadata-Version: 2.1
Name: muse-pytorch
Version: 0.0.1
Summary: Pytorch version of MUSE
Home-page: https://github.com/Nico995/MUSE-pytorch
Author: Nicola Occelli
Author-email: nicola.occelli@ulb.be
Project-URL: Bug Tracker, https://github.com/Nico995/MUSE-pytorch/issues
Classifier: Programming Language :: Python :: 3
Classifier: License :: OSI Approved :: MIT License
Classifier: Operating System :: OS Independent
Classifier: Development Status :: 4 - Beta
Classifier: Environment :: GPU :: NVIDIA CUDA :: 10.2
Classifier: Natural Language :: English
Requires-Python: >=3.6
License-File: LICENCE
